seqcore/__init__.py
seqcore/alignment/__init__.py
seqcore/core/__init__.py
seqcore/core/arrays.py
seqcore/core/device.py
seqcore/core/kmers.py
seqcore/core/operations.py
seqcore/core/structure.py
seqcore/io/__init__.py
seqcore/molecules/__init__.py
seqcore/phylogenetics/__init__.py
seqcore/population/__init__.py
seqcore/structure/__init__.py
seqcore-0.3.0.dist-info/METADATA
seqcore-0.3.0.dist-info/WHEEL
seqcore-0.3.0.dist-info/licenses/LICENSE
seqcore-0.3.0.dist-info/RECORD
