Metadata-Version: 2.4
Name: seqcore
Version: 0.3.0
Summary: High-performance biological sequence analysis library with GPU acceleration
Project-URL: Homepage, https://github.com/pritampanda15/Seqcore
Project-URL: Documentation, https://Seqcore.readthedocs.io
Project-URL: Repository, https://github.com/pritampanda15/Seqcore
Project-URL: Issues, https://github.com/pritampanda15/Seqcore/issues
Author-email: "Dr. Pritam Kumar Panda" <pritam@stanford.edu>
Maintainer-email: "Dr. Pritam Kumar Panda" <pritam@stanford.edu>
License: MIT
License-File: LICENSE
Keywords: bioinformatics,drug-design,genomics,gpu-acceleration,proteomics,sequence-analysis,structural-biology
Classifier: Development Status :: 4 - Beta
Classifier: Intended Audience :: Developers
Classifier: Intended Audience :: Science/Research
Classifier: License :: OSI Approved :: MIT License
Classifier: Operating System :: OS Independent
Classifier: Programming Language :: Python :: 3
Classifier: Programming Language :: Python :: 3.9
Classifier: Programming Language :: Python :: 3.10
Classifier: Programming Language :: Python :: 3.11
Classifier: Programming Language :: Python :: 3.12
Classifier: Topic :: Scientific/Engineering :: Bio-Informatics
Classifier: Topic :: Scientific/Engineering :: Chemistry
Requires-Python: >=3.9
Requires-Dist: numpy<2.0.0,>=1.22.0
Provides-Extra: dev
Requires-Dist: bandit>=1.7.0; extra == 'dev'
Requires-Dist: biopython>=1.79; extra == 'dev'
Requires-Dist: black>=23.0.0; extra == 'dev'
Requires-Dist: h5py>=3.0.0; extra == 'dev'
Requires-Dist: isort>=5.12.0; extra == 'dev'
Requires-Dist: mypy>=1.0.0; extra == 'dev'
Requires-Dist: pandas<2.2.0,>=1.5.0; extra == 'dev'
Requires-Dist: pip-audit>=2.6.0; extra == 'dev'
Requires-Dist: pytest-cov>=4.0.0; extra == 'dev'
Requires-Dist: pytest>=7.0.0; extra == 'dev'
Requires-Dist: ruff>=0.1.0; extra == 'dev'
Provides-Extra: docs
Requires-Dist: myst-parser>=1.0.0; extra == 'docs'
Requires-Dist: sphinx-rtd-theme>=1.0.0; extra == 'docs'
Requires-Dist: sphinx>=6.0.0; extra == 'docs'
Provides-Extra: full
Requires-Dist: biopython>=1.79; extra == 'full'
Requires-Dist: h5py>=3.0.0; extra == 'full'
Requires-Dist: pandas<2.2.0,>=1.5.0; extra == 'full'
Provides-Extra: gpu
Requires-Dist: cupy>=11.0.0; extra == 'gpu'
Provides-Extra: molecules
Requires-Dist: rdkit>=2022.03.1; (python_version >= '3.10') and extra == 'molecules'
Provides-Extra: structure
Requires-Dist: mdanalysis>=2.0.0; extra == 'structure'
